hello_lib/__init__.py
hello_lib/hello.py
test_python_lib-0.1.2.dist-info/METADATA
test_python_lib-0.1.2.dist-info/WHEEL
test_python_lib-0.1.2.dist-info/top_level.txt
test_python_lib-0.1.2.dist-info/RECORD
