Metadata-Version: 2.1
Name: test-python-lib
Version: 0.1.2
Summary: My first Python library
Home-page: UNKNOWN
Author: Me
License: MIT
Platform: UNKNOWN
